{
  "count": 600,
  "trees": [
    {
      "u": 0.2592,
      "v": 0.00641,
      "height_m": 12.17,
      "radius_m": 3.89
    },
    {
      "u": 0.48257,
      "v": 0.00302,
      "height_m": 13.47,
      "radius_m": 3.86
    },
    {
      "u": 0.31297,
      "v": 0.01959,
      "height_m": 9.34,
      "radius_m": 3.43
    },
    {
      "u": 0.35999,
      "v": 0.02102,
      "height_m": 12.92,
      "radius_m": 3.88
    },
    {
      "u": 0.3754,
      "v": 0.01744,
      "height_m": 13.34,
      "radius_m": 3.85
    },
    {
      "u": 0.39162,
      "v": 0.02004,
      "height_m": 12.49,
      "radius_m": 3.69
    },
    {
      "u": 0.41677,
      "v": 0.02303,
      "height_m": 11.25,
      "radius_m": 3.86
    },
    {
      "u": 0.43769,
      "v": 0.02519,
      "height_m": 11.36,
      "radius_m": 3.56
    },
    {
      "u": 0.46068,
      "v": 0.0255,
      "height_m": 10.3,
      "radius_m": 3.27
    },
    {
      "u": 0.27391,
      "v": 0.03598,
      "height_m": 13.87,
      "radius_m": 3.99
    },
    {
      "u": 0.39079,
      "v": 0.03006,
      "height_m": 11.01,
      "radius_m": 3.76
    },
    {
      "u": 0.4423,
      "v": 0.0351,
      "height_m": 11.55,
      "radius_m": 3.39
    },
    {
      "u": 0.45123,
      "v": 0.0358,
      "height_m": 10.09,
      "radius_m": 3.52
    },
    {
      "u": 0.26363,
      "v": 0.05156,
      "height_m": 7.76,
      "radius_m": 2.63
    },
    {
      "u": 0.30334,
      "v": 0.04923,
      "height_m": 13.64,
      "radius_m": 3.94
    },
    {
      "u": 0.31573,
      "v": 0.04621,
      "height_m": 12.24,
      "radius_m": 3.96
    },
    {
      "u": 0.46883,
      "v": 0.04879,
      "height_m": 12.71,
      "radius_m": 3.82
    },
    {
      "u": 0.48093,
      "v": 0.04634,
      "height_m": 11.42,
      "radius_m": 3.61
    },
    {
      "u": 0.51839,
      "v": 0.05344,
      "height_m": 10.63,
      "radius_m": 2.96
    },
    {
      "u": 0.552,
      "v": 0.05076,
      "height_m": 9.16,
      "radius_m": 2.97
    },
    {
      "u": 0.31393,
      "v": 0.06457,
      "height_m": 13.41,
      "radius_m": 3.98
    },
    {
      "u": 0.40941,
      "v": 0.06628,
      "height_m": 11.86,
      "radius_m": 3.39
    },
    {
      "u": 0.42486,
      "v": 0.05796,
      "height_m": 12.49,
      "radius_m": 3.99
    },
    {
      "u": 0.43596,
      "v": 0.05935,
      "height_m": 12.88,
      "radius_m": 3.77
    },
    {
      "u": 0.44988,
      "v": 0.05942,
      "height_m": 11.72,
      "radius_m": 3.58
    },
    {
      "u": 0.48252,
      "v": 0.06533,
      "height_m": 12.75,
      "radius_m": 3.72
    },
    {
      "u": 0.49195,
      "v": 0.05896,
      "height_m": 10.48,
      "radius_m": 3.72
    },
    {
      "u": 0.54795,
      "v": 0.06216,
      "height_m": 11.97,
      "radius_m": 3.46
    },
    {
      "u": 0.41309,
      "v": 0.07593,
      "height_m": 12.59,
      "radius_m": 3.9
    },
    {
      "u": 0.44765,
      "v": 0.07594,
      "height_m": 12.26,
      "radius_m": 3.68
    },
    {
      "u": 0.4949,
      "v": 0.07538,
      "height_m": 11.7,
      "radius_m": 3.5
    },
    {
      "u": 0.30551,
      "v": 0.08734,
      "height_m": 11.08,
      "radius_m": 3.62
    },
    {
      "u": 0.31922,
      "v": 0.09346,
      "height_m": 10.0,
      "radius_m": 3.21
    },
    {
      "u": 0.52609,
      "v": 0.09477,
      "height_m": 11.07,
      "radius_m": 4.0
    },
    {
      "u": 0.61444,
      "v": 0.09469,
      "height_m": 10.13,
      "radius_m": 2.85
    },
    {
      "u": 0.12478,
      "v": 0.10237,
      "height_m": 9.28,
      "radius_m": 3.41
    },
    {
      "u": 0.31841,
      "v": 0.10605,
      "height_m": 9.18,
      "radius_m": 3.0
    },
    {
      "u": 0.38557,
      "v": 0.10169,
      "height_m": 9.76,
      "radius_m": 3.46
    },
    {
      "u": 0.45039,
      "v": 0.10754,
      "height_m": 10.98,
      "radius_m": 3.91
    },
    {
      "u": 0.52548,
      "v": 0.10641,
      "height_m": 11.8,
      "radius_m": 3.99
    },
    {
      "u": 0.56882,
      "v": 0.10383,
      "height_m": 11.21,
      "radius_m": 3.86
    },
    {
      "u": 0.11684,
      "v": 0.11678,
      "height_m": 10.47,
      "radius_m": 3.09
    },
    {
      "u": 0.31432,
      "v": 0.11886,
      "height_m": 8.03,
      "radius_m": 2.55
    },
    {
      "u": 0.34925,
      "v": 0.11582,
      "height_m": 10.35,
      "radius_m": 3.43
    },
    {
      "u": 0.55198,
      "v": 0.11715,
      "height_m": 12.54,
      "radius_m": 3.63
    },
    {
      "u": 0.56436,
      "v": 0.11621,
      "height_m": 12.64,
      "radius_m": 3.82
    },
    {
      "u": 0.5961,
      "v": 0.11782,
      "height_m": 10.41,
      "radius_m": 3.68
    },
    {
      "u": 0.20503,
      "v": 0.12844,
      "height_m": 7.11,
      "radius_m": 2.68
    },
    {
      "u": 0.3268,
      "v": 0.13023,
      "height_m": 9.29,
      "radius_m": 2.82
    },
    {
      "u": 0.5311,
      "v": 0.13131,
      "height_m": 11.31,
      "radius_m": 3.9
    },
    {
      "u": 0.55795,
      "v": 0.13018,
      "height_m": 8.44,
      "radius_m": 3.14
    },
    {
      "u": 0.57004,
      "v": 0.12733,
      "height_m": 9.76,
      "radius_m": 3.47
    },
    {
      "u": 0.12579,
      "v": 0.14939,
      "height_m": 11.43,
      "radius_m": 3.75
    },
    {
      "u": 0.14955,
      "v": 0.14291,
      "height_m": 13.0,
      "radius_m": 3.95
    },
    {
      "u": 0.29599,
      "v": 0.14286,
      "height_m": 11.22,
      "radius_m": 3.61
    },
    {
      "u": 0.30925,
      "v": 0.14621,
      "height_m": 9.94,
      "radius_m": 3.6
    },
    {
      "u": 0.39279,
      "v": 0.14797,
      "height_m": 11.13,
      "radius_m": 3.72
    },
    {
      "u": 0.40635,
      "v": 0.14997,
      "height_m": 10.05,
      "radius_m": 3.64
    },
    {
      "u": 0.60527,
      "v": 0.14977,
      "height_m": 9.32,
      "radius_m": 3.21
    },
    {
      "u": 0.61837,
      "v": 0.14398,
      "height_m": 11.78,
      "radius_m": 3.38
    },
    {
      "u": 0.68405,
      "v": 0.14407,
      "height_m": 6.67,
      "radius_m": 2.49
    },
    {
      "u": 0.17331,
      "v": 0.16185,
      "height_m": 11.86,
      "radius_m": 3.78
    },
    {
      "u": 0.23971,
      "v": 0.15558,
      "height_m": 10.16,
      "radius_m": 3.24
    },
    {
      "u": 0.26008,
      "v": 0.15782,
      "height_m": 11.5,
      "radius_m": 3.58
    },
    {
      "u": 0.33615,
      "v": 0.15985,
      "height_m": 11.86,
      "radius_m": 3.99
    },
    {
      "u": 0.51676,
      "v": 0.16225,
      "height_m": 10.28,
      "radius_m": 3.13
    },
    {
      "u": 0.54185,
      "v": 0.16068,
      "height_m": 10.53,
      "radius_m": 3.8
    },
    {
      "u": 0.61937,
      "v": 0.16079,
      "height_m": 11.61,
      "radius_m": 3.7
    },
    {
      "u": 0.64251,
      "v": 0.16339,
      "height_m": 11.12,
      "radius_m": 3.74
    },
    {
      "u": 0.142,
      "v": 0.17744,
      "height_m": 13.7,
      "radius_m": 3.96
    },
    {
      "u": 0.16471,
      "v": 0.17618,
      "height_m": 10.47,
      "radius_m": 3.77
    },
    {
      "u": 0.29628,
      "v": 0.17514,
      "height_m": 10.59,
      "radius_m": 3.27
    },
    {
      "u": 0.36147,
      "v": 0.17574,
      "height_m": 10.17,
      "radius_m": 2.82
    },
    {
      "u": 0.53982,
      "v": 0.17752,
      "height_m": 11.77,
      "radius_m": 3.9
    },
    {
      "u": 0.56469,
      "v": 0.1701,
      "height_m": 11.29,
      "radius_m": 3.15
    },
    {
      "u": 0.57351,
      "v": 0.17649,
      "height_m": 8.4,
      "radius_m": 2.54
    },
    {
      "u": 0.59261,
      "v": 0.1737,
      "height_m": 9.06,
      "radius_m": 2.71
    },
    {
      "u": 0.68635,
      "v": 0.16931,
      "height_m": 10.29,
      "radius_m": 3.02
    },
    {
      "u": 0.09354,
      "v": 0.18922,
      "height_m": 11.48,
      "radius_m": 3.82
    },
    {
      "u": 0.24178,
      "v": 0.19221,
      "height_m": 12.79,
      "radius_m": 3.86
    },
    {
      "u": 0.28289,
      "v": 0.19039,
      "height_m": 9.02,
      "radius_m": 3.13
    },
    {
      "u": 0.71386,
      "v": 0.19203,
      "height_m": 9.43,
      "radius_m": 2.66
    },
    {
      "u": 0.1462,
      "v": 0.20348,
      "height_m": 11.42,
      "radius_m": 3.88
    },
    {
      "u": 0.59674,
      "v": 0.20296,
      "height_m": 9.83,
      "radius_m": 3.55
    },
    {
      "u": 0.08541,
      "v": 0.2185,
      "height_m": 11.33,
      "radius_m": 3.97
    },
    {
      "u": 0.50195,
      "v": 0.2123,
      "height_m": 10.68,
      "radius_m": 3.63
    },
    {
      "u": 0.59791,
      "v": 0.21603,
      "height_m": 10.92,
      "radius_m": 3.71
    },
    {
      "u": 0.61471,
      "v": 0.21299,
      "height_m": 11.58,
      "radius_m": 3.83
    },
    {
      "u": 0.62996,
      "v": 0.21467,
      "height_m": 10.86,
      "radius_m": 3.92
    },
    {
      "u": 0.67561,
      "v": 0.21223,
      "height_m": 8.52,
      "radius_m": 2.79
    },
    {
      "u": 0.08101,
      "v": 0.23142,
      "height_m": 13.35,
      "radius_m": 3.95
    },
    {
      "u": 0.09254,
      "v": 0.22521,
      "height_m": 12.65,
      "radius_m": 3.96
    },
    {
      "u": 0.12742,
      "v": 0.22825,
      "height_m": 11.43,
      "radius_m": 3.98
    },
    {
      "u": 0.1373,
      "v": 0.22688,
      "height_m": 10.19,
      "radius_m": 3.49
    },
    {
      "u": 0.24229,
      "v": 0.22829,
      "height_m": 12.58,
      "radius_m": 3.93
    },
    {
      "u": 0.49309,
      "v": 0.23254,
      "height_m": 12.98,
      "radius_m": 3.74
    },
    {
      "u": 0.53941,
      "v": 0.2273,
      "height_m": 10.21,
      "radius_m": 2.85
    },
    {
      "u": 0.70818,
      "v": 0.23379,
      "height_m": 10.76,
      "radius_m": 3.23
    },
    {
      "u": 0.72038,
      "v": 0.22701,
      "height_m": 10.65,
      "radius_m": 3.38
    },
    {
      "u": 0.72555,
      "v": 0.22512,
      "height_m": 10.22,
      "radius_m": 3.32
    },
    {
      "u": 0.07417,
      "v": 0.24441,
      "height_m": 7.81,
      "radius_m": 2.64
    },
    {
      "u": 0.09142,
      "v": 0.24783,
      "height_m": 13.87,
      "radius_m": 3.99
    },
    {
      "u": 0.28658,
      "v": 0.24443,
      "height_m": 8.9,
      "radius_m": 2.73
    },
    {
      "u": 0.47043,
      "v": 0.2462,
      "height_m": 7.68,
      "radius_m": 2.68
    },
    {
      "u": 0.05231,
      "v": 0.25252,
      "height_m": 13.13,
      "radius_m": 3.81
    },
    {
      "u": 0.12632,
      "v": 0.25704,
      "height_m": 11.61,
      "radius_m": 3.99
    },
    {
      "u": 0.14641,
      "v": 0.26022,
      "height_m": 13.97,
      "radius_m": 4.0
    },
    {
      "u": 0.1907,
      "v": 0.25276,
      "height_m": 13.19,
      "radius_m": 4.0
    },
    {
      "u": 0.42953,
      "v": 0.2601,
      "height_m": 11.92,
      "radius_m": 3.66
    },
    {
      "u": 0.43725,
      "v": 0.25814,
      "height_m": 13.31,
      "radius_m": 3.9
    },
    {
      "u": 0.46379,
      "v": 0.25965,
      "height_m": 9.03,
      "radius_m": 3.31
    },
    {
      "u": 0.47413,
      "v": 0.25881,
      "height_m": 7.39,
      "radius_m": 2.7
    },
    {
      "u": 0.48353,
      "v": 0.25879,
      "height_m": 10.17,
      "radius_m": 3.4
    },
    {
      "u": 0.49447,
      "v": 0.26157,
      "height_m": 12.47,
      "radius_m": 3.86
    },
    {
      "u": 0.52839,
      "v": 0.25768,
      "height_m": 11.9,
      "radius_m": 3.77
    },
    {
      "u": 0.54072,
      "v": 0.25529,
      "height_m": 11.51,
      "radius_m": 3.68
    },
    {
      "u": 0.5829,
      "v": 0.25308,
      "height_m": 9.65,
      "radius_m": 3.11
    },
    {
      "u": 0.66295,
      "v": 0.25538,
      "height_m": 10.95,
      "radius_m": 3.16
    },
    {
      "u": 0.67133,
      "v": 0.26169,
      "height_m": 11.49,
      "radius_m": 3.29
    },
    {
      "u": 0.68457,
      "v": 0.26017,
      "height_m": 12.39,
      "radius_m": 3.92
    },
    {
      "u": 0.74686,
      "v": 0.25294,
      "height_m": 9.45,
      "radius_m": 2.88
    },
    {
      "u": 0.78659,
      "v": 0.25359,
      "height_m": 9.44,
      "radius_m": 2.65
    },
    {
      "u": 0.13632,
      "v": 0.2734,
      "height_m": 12.35,
      "radius_m": 4.0
    },
    {
      "u": 0.21509,
      "v": 0.26646,
      "height_m": 10.51,
      "radius_m": 3.59
    },
    {
      "u": 0.27507,
      "v": 0.27154,
      "height_m": 13.05,
      "radius_m": 4.0
    },
    {
      "u": 0.49126,
      "v": 0.27325,
      "height_m": 11.52,
      "radius_m": 3.84
    },
    {
      "u": 0.52571,
      "v": 0.27533,
      "height_m": 11.85,
      "radius_m": 3.61
    },
    {
      "u": 0.55344,
      "v": 0.26886,
      "height_m": 13.42,
      "radius_m": 3.83
    },
    {
      "u": 0.63632,
      "v": 0.26617,
      "height_m": 11.44,
      "radius_m": 3.24
    },
    {
      "u": 0.66314,
      "v": 0.27115,
      "height_m": 11.3,
      "radius_m": 3.93
    },
    {
      "u": 0.70218,
      "v": 0.2661,
      "height_m": 11.93,
      "radius_m": 3.6
    },
    {
      "u": 0.10675,
      "v": 0.28365,
      "height_m": 12.38,
      "radius_m": 4.0
    },
    {
      "u": 0.24177,
      "v": 0.2888,
      "height_m": 8.13,
      "radius_m": 2.71
    },
    {
      "u": 0.27041,
      "v": 0.28239,
      "height_m": 12.55,
      "radius_m": 4.0
    },
    {
      "u": 0.33083,
      "v": 0.28749,
      "height_m": 10.17,
      "radius_m": 3.61
    },
    {
      "u": 0.4404,
      "v": 0.28022,
      "height_m": 12.6,
      "radius_m": 3.63
    },
    {
      "u": 0.48572,
      "v": 0.28634,
      "height_m": 12.0,
      "radius_m": 3.62
    },
    {
      "u": 0.67422,
      "v": 0.28006,
      "height_m": 10.35,
      "radius_m": 3.68
    },
    {
      "u": 0.71826,
      "v": 0.28223,
      "height_m": 12.67,
      "radius_m": 3.89
    },
    {
      "u": 0.73502,
      "v": 0.28176,
      "height_m": 11.78,
      "radius_m": 3.44
    },
    {
      "u": 0.77498,
      "v": 0.28928,
      "height_m": 9.68,
      "radius_m": 2.71
    },
    {
      "u": 0.05387,
      "v": 0.29919,
      "height_m": 9.61,
      "radius_m": 3.38
    },
    {
      "u": 0.08575,
      "v": 0.29779,
      "height_m": 13.45,
      "radius_m": 4.0
    },
    {
      "u": 0.11489,
      "v": 0.30014,
      "height_m": 12.14,
      "radius_m": 4.0
    },
    {
      "u": 0.20905,
      "v": 0.29827,
      "height_m": 10.53,
      "radius_m": 2.92
    },
    {
      "u": 0.24804,
      "v": 0.29602,
      "height_m": 11.26,
      "radius_m": 3.58
    },
    {
      "u": 0.27197,
      "v": 0.30236,
      "height_m": 11.15,
      "radius_m": 4.0
    },
    {
      "u": 0.29663,
      "v": 0.29842,
      "height_m": 12.76,
      "radius_m": 3.97
    },
    {
      "u": 0.32772,
      "v": 0.29591,
      "height_m": 10.0,
      "radius_m": 3.67
    },
    {
      "u": 0.35748,
      "v": 0.29635,
      "height_m": 12.36,
      "radius_m": 3.5
    },
    {
      "u": 0.36855,
      "v": 0.30089,
      "height_m": 11.5,
      "radius_m": 3.7
    },
    {
      "u": 0.39457,
      "v": 0.30259,
      "height_m": 7.62,
      "radius_m": 2.58
    },
    {
      "u": 0.42633,
      "v": 0.29491,
      "height_m": 12.4,
      "radius_m": 3.87
    },
    {
      "u": 0.47522,
      "v": 0.30333,
      "height_m": 13.21,
      "radius_m": 3.92
    },
    {
      "u": 0.54852,
      "v": 0.3006,
      "height_m": 10.19,
      "radius_m": 3.66
    },
    {
      "u": 0.57386,
      "v": 0.30075,
      "height_m": 11.49,
      "radius_m": 3.51
    },
    {
      "u": 0.58374,
      "v": 0.30096,
      "height_m": 9.67,
      "radius_m": 3.49
    },
    {
      "u": 0.65374,
      "v": 0.30021,
      "height_m": 11.28,
      "radius_m": 3.21
    },
    {
      "u": 0.66904,
      "v": 0.29836,
      "height_m": 12.18,
      "radius_m": 3.79
    },
    {
      "u": 0.33125,
      "v": 0.31716,
      "height_m": 10.97,
      "radius_m": 3.15
    },
    {
      "u": 0.46207,
      "v": 0.31245,
      "height_m": 11.59,
      "radius_m": 3.93
    },
    {
      "u": 0.66275,
      "v": 0.31151,
      "height_m": 10.89,
      "radius_m": 3.82
    },
    {
      "u": 0.69445,
      "v": 0.31716,
      "height_m": 13.36,
      "radius_m": 3.96
    },
    {
      "u": 0.33848,
      "v": 0.32633,
      "height_m": 9.68,
      "radius_m": 2.81
    },
    {
      "u": 0.61862,
      "v": 0.32958,
      "height_m": 11.97,
      "radius_m": 3.84
    },
    {
      "u": 0.81344,
      "v": 0.33005,
      "height_m": 11.03,
      "radius_m": 3.65
    },
    {
      "u": 0.84811,
      "v": 0.33003,
      "height_m": 11.16,
      "radius_m": 3.85
    },
    {
      "u": 0.06498,
      "v": 0.3434,
      "height_m": 13.31,
      "radius_m": 3.93
    },
    {
      "u": 0.18569,
      "v": 0.34017,
      "height_m": 13.19,
      "radius_m": 3.87
    },
    {
      "u": 0.24741,
      "v": 0.34179,
      "height_m": 9.83,
      "radius_m": 3.58
    },
    {
      "u": 0.63724,
      "v": 0.34177,
      "height_m": 11.06,
      "radius_m": 3.82
    },
    {
      "u": 0.68583,
      "v": 0.34116,
      "height_m": 11.17,
      "radius_m": 3.76
    },
    {
      "u": 0.70489,
      "v": 0.34018,
      "height_m": 11.04,
      "radius_m": 3.09
    },
    {
      "u": 0.71527,
      "v": 0.33978,
      "height_m": 13.76,
      "radius_m": 3.95
    },
    {
      "u": 0.75041,
      "v": 0.33754,
      "height_m": 11.19,
      "radius_m": 3.97
    },
    {
      "u": 0.06299,
      "v": 0.35254,
      "height_m": 12.23,
      "radius_m": 3.77
    },
    {
      "u": 0.07361,
      "v": 0.35814,
      "height_m": 11.4,
      "radius_m": 3.28
    },
    {
      "u": 0.16016,
      "v": 0.35643,
      "height_m": 13.9,
      "radius_m": 4.0
    },
    {
      "u": 0.28018,
      "v": 0.34931,
      "height_m": 10.28,
      "radius_m": 3.25
    },
    {
      "u": 0.29448,
      "v": 0.3577,
      "height_m": 10.68,
      "radius_m": 3.72
    },
    {
      "u": 0.35926,
      "v": 0.34995,
      "height_m": 11.05,
      "radius_m": 3.93
    },
    {
      "u": 0.52593,
      "v": 0.35814,
      "height_m": 11.3,
      "radius_m": 3.27
    },
    {
      "u": 0.82709,
      "v": 0.35654,
      "height_m": 12.86,
      "radius_m": 3.78
    },
    {
      "u": 0.12716,
      "v": 0.3657,
      "height_m": 13.51,
      "radius_m": 4.0
    },
    {
      "u": 0.13775,
      "v": 0.36728,
      "height_m": 12.36,
      "radius_m": 3.99
    },
    {
      "u": 0.30926,
      "v": 0.36961,
      "height_m": 10.89,
      "radius_m": 3.03
    },
    {
      "u": 0.31813,
      "v": 0.36997,
      "height_m": 11.98,
      "radius_m": 3.64
    },
    {
      "u": 0.32487,
      "v": 0.36565,
      "height_m": 10.86,
      "radius_m": 3.89
    },
    {
      "u": 0.36026,
      "v": 0.3651,
      "height_m": 9.89,
      "radius_m": 3.55
    },
    {
      "u": 0.49296,
      "v": 0.36612,
      "height_m": 8.33,
      "radius_m": 2.6
    },
    {
      "u": 0.76952,
      "v": 0.3643,
      "height_m": 12.76,
      "radius_m": 3.95
    },
    {
      "u": 0.89375,
      "v": 0.36694,
      "height_m": 10.31,
      "radius_m": 3.49
    },
    {
      "u": 0.90634,
      "v": 0.36817,
      "height_m": 11.01,
      "radius_m": 3.6
    },
    {
      "u": 0.9183,
      "v": 0.37109,
      "height_m": 12.74,
      "radius_m": 3.93
    },
    {
      "u": 0.20199,
      "v": 0.38678,
      "height_m": 11.96,
      "radius_m": 3.89
    },
    {
      "u": 0.34086,
      "v": 0.3779,
      "height_m": 9.3,
      "radius_m": 2.54
    },
    {
      "u": 0.43715,
      "v": 0.38401,
      "height_m": 10.72,
      "radius_m": 3.5
    },
    {
      "u": 0.6761,
      "v": 0.37722,
      "height_m": 12.01,
      "radius_m": 3.73
    },
    {
      "u": 0.70906,
      "v": 0.37873,
      "height_m": 11.42,
      "radius_m": 3.91
    },
    {
      "u": 0.74232,
      "v": 0.38505,
      "height_m": 11.97,
      "radius_m": 3.98
    },
    {
      "u": 0.77374,
      "v": 0.38591,
      "height_m": 12.98,
      "radius_m": 3.99
    },
    {
      "u": 0.83072,
      "v": 0.38446,
      "height_m": 11.92,
      "radius_m": 3.82
    },
    {
      "u": 0.88143,
      "v": 0.3786,
      "height_m": 12.23,
      "radius_m": 3.93
    },
    {
      "u": 0.92763,
      "v": 0.38041,
      "height_m": 11.09,
      "radius_m": 3.22
    },
    {
      "u": 0.47973,
      "v": 0.39544,
      "height_m": 9.42,
      "radius_m": 3.46
    },
    {
      "u": 0.68,
      "v": 0.39289,
      "height_m": 8.09,
      "radius_m": 2.97
    },
    {
      "u": 0.7649,
      "v": 0.39651,
      "height_m": 12.39,
      "radius_m": 3.99
    },
    {
      "u": 0.89238,
      "v": 0.39201,
      "height_m": 11.45,
      "radius_m": 3.51
    },
    {
      "u": 0.96023,
      "v": 0.39439,
      "height_m": 7.09,
      "radius_m": 2.65
    },
    {
      "u": 0.13946,
      "v": 0.41405,
      "height_m": 9.32,
      "radius_m": 2.74
    },
    {
      "u": 0.55841,
      "v": 0.4063,
      "height_m": 11.73,
      "radius_m": 3.52
    },
    {
      "u": 0.69141,
      "v": 0.407,
      "height_m": 13.18,
      "radius_m": 3.96
    },
    {
      "u": 0.85066,
      "v": 0.40972,
      "height_m": 13.18,
      "radius_m": 3.83
    },
    {
      "u": 0.89071,
      "v": 0.41017,
      "height_m": 13.02,
      "radius_m": 3.77
    },
    {
      "u": 0.90893,
      "v": 0.41042,
      "height_m": 13.08,
      "radius_m": 3.72
    },
    {
      "u": 0.93896,
      "v": 0.41283,
      "height_m": 8.23,
      "radius_m": 2.66
    },
    {
      "u": 0.21384,
      "v": 0.42579,
      "height_m": 8.78,
      "radius_m": 2.83
    },
    {
      "u": 0.47455,
      "v": 0.41995,
      "height_m": 10.17,
      "radius_m": 3.44
    },
    {
      "u": 0.53889,
      "v": 0.42628,
      "height_m": 8.3,
      "radius_m": 3.08
    },
    {
      "u": 0.55036,
      "v": 0.42643,
      "height_m": 9.58,
      "radius_m": 3.49
    },
    {
      "u": 0.86258,
      "v": 0.42091,
      "height_m": 12.39,
      "radius_m": 3.91
    },
    {
      "u": 0.8697,
      "v": 0.42344,
      "height_m": 13.02,
      "radius_m": 3.81
    },
    {
      "u": 0.20508,
      "v": 0.43328,
      "height_m": 12.08,
      "radius_m": 4.0
    },
    {
      "u": 0.25307,
      "v": 0.43323,
      "height_m": 12.81,
      "radius_m": 3.67
    },
    {
      "u": 0.77334,
      "v": 0.44098,
      "height_m": 13.05,
      "radius_m": 3.98
    },
    {
      "u": 0.831,
      "v": 0.43487,
      "height_m": 10.68,
      "radius_m": 3.81
    },
    {
      "u": 0.83899,
      "v": 0.44037,
      "height_m": 11.88,
      "radius_m": 3.89
    },
    {
      "u": 0.8581,
      "v": 0.43539,
      "height_m": 10.04,
      "radius_m": 3.57
    },
    {
      "u": 0.89117,
      "v": 0.43574,
      "height_m": 11.64,
      "radius_m": 3.36
    },
    {
      "u": 0.21505,
      "v": 0.44921,
      "height_m": 11.32,
      "radius_m": 3.98
    },
    {
      "u": 0.33914,
      "v": 0.45233,
      "height_m": 9.6,
      "radius_m": 3.42
    },
    {
      "u": 0.51596,
      "v": 0.44914,
      "height_m": 13.72,
      "radius_m": 3.98
    },
    {
      "u": 0.68449,
      "v": 0.44729,
      "height_m": 13.22,
      "radius_m": 3.86
    },
    {
      "u": 0.72456,
      "v": 0.45282,
      "height_m": 8.59,
      "radius_m": 3.02
    },
    {
      "u": 0.78007,
      "v": 0.45506,
      "height_m": 12.64,
      "radius_m": 3.86
    },
    {
      "u": 0.83056,
      "v": 0.45087,
      "height_m": 12.93,
      "radius_m": 3.83
    },
    {
      "u": 0.87307,
      "v": 0.44836,
      "height_m": 12.02,
      "radius_m": 3.81
    },
    {
      "u": 0.92554,
      "v": 0.44659,
      "height_m": 8.81,
      "radius_m": 3.22
    },
    {
      "u": 0.96047,
      "v": 0.45514,
      "height_m": 9.73,
      "radius_m": 2.89
    },
    {
      "u": 0.01329,
      "v": 0.46578,
      "height_m": 8.59,
      "radius_m": 2.59
    },
    {
      "u": 0.3358,
      "v": 0.46715,
      "height_m": 10.92,
      "radius_m": 3.6
    },
    {
      "u": 0.54093,
      "v": 0.464,
      "height_m": 12.58,
      "radius_m": 3.68
    },
    {
      "u": 0.79806,
      "v": 0.46897,
      "height_m": 11.08,
      "radius_m": 3.72
    },
    {
      "u": 0.18305,
      "v": 0.47594,
      "height_m": 7.29,
      "radius_m": 2.6
    },
    {
      "u": 0.46493,
      "v": 0.4766,
      "height_m": 7.62,
      "radius_m": 2.58
    },
    {
      "u": 0.83036,
      "v": 0.47729,
      "height_m": 12.37,
      "radius_m": 3.89
    },
    {
      "u": 0.88547,
      "v": 0.47814,
      "height_m": 10.55,
      "radius_m": 3.68
    },
    {
      "u": 0.9584,
      "v": 0.48272,
      "height_m": 10.52,
      "radius_m": 3.22
    },
    {
      "u": 0.09814,
      "v": 0.48835,
      "height_m": 12.99,
      "radius_m": 3.78
    },
    {
      "u": 0.22837,
      "v": 0.49182,
      "height_m": 13.04,
      "radius_m": 3.72
    },
    {
      "u": 0.34695,
      "v": 0.49534,
      "height_m": 7.63,
      "radius_m": 2.56
    },
    {
      "u": 0.65931,
      "v": 0.48828,
      "height_m": 12.18,
      "radius_m": 3.68
    },
    {
      "u": 0.73708,
      "v": 0.49152,
      "height_m": 9.44,
      "radius_m": 3.13
    },
    {
      "u": 0.74844,
      "v": 0.4884,
      "height_m": 10.32,
      "radius_m": 3.57
    },
    {
      "u": 0.80848,
      "v": 0.49504,
      "height_m": 12.59,
      "radius_m": 3.84
    },
    {
      "u": 0.85132,
      "v": 0.49733,
      "height_m": 11.25,
      "radius_m": 3.75
    },
    {
      "u": 0.90769,
      "v": 0.48931,
      "height_m": 10.08,
      "radius_m": 3.3
    },
    {
      "u": 0.95372,
      "v": 0.49633,
      "height_m": 12.21,
      "radius_m": 3.84
    },
    {
      "u": 0.95961,
      "v": 0.48975,
      "height_m": 8.29,
      "radius_m": 2.96
    },
    {
      "u": 0.07061,
      "v": 0.50588,
      "height_m": 9.17,
      "radius_m": 2.84
    },
    {
      "u": 0.19685,
      "v": 0.50865,
      "height_m": 12.21,
      "radius_m": 3.93
    },
    {
      "u": 0.36296,
      "v": 0.50339,
      "height_m": 8.32,
      "radius_m": 3.09
    },
    {
      "u": 0.40192,
      "v": 0.50812,
      "height_m": 9.85,
      "radius_m": 3.2
    },
    {
      "u": 0.54677,
      "v": 0.51105,
      "height_m": 11.69,
      "radius_m": 3.42
    },
    {
      "u": 0.91806,
      "v": 0.50573,
      "height_m": 12.13,
      "radius_m": 3.85
    },
    {
      "u": 0.45767,
      "v": 0.5225,
      "height_m": 11.13,
      "radius_m": 3.7
    },
    {
      "u": 0.52613,
      "v": 0.52268,
      "height_m": 10.4,
      "radius_m": 3.72
    },
    {
      "u": 0.71821,
      "v": 0.52111,
      "height_m": 7.74,
      "radius_m": 2.71
    },
    {
      "u": 0.07488,
      "v": 0.53216,
      "height_m": 8.85,
      "radius_m": 2.7
    },
    {
      "u": 0.10733,
      "v": 0.53864,
      "height_m": 11.61,
      "radius_m": 3.59
    },
    {
      "u": 0.43666,
      "v": 0.53807,
      "height_m": 9.03,
      "radius_m": 2.71
    },
    {
      "u": 0.48693,
      "v": 0.53641,
      "height_m": 11.24,
      "radius_m": 3.15
    },
    {
      "u": 0.49697,
      "v": 0.53603,
      "height_m": 9.94,
      "radius_m": 2.98
    },
    {
      "u": 0.5749,
      "v": 0.53322,
      "height_m": 11.97,
      "radius_m": 3.82
    },
    {
      "u": 0.78258,
      "v": 0.53194,
      "height_m": 10.86,
      "radius_m": 3.42
    },
    {
      "u": 0.90279,
      "v": 0.53599,
      "height_m": 11.42,
      "radius_m": 3.59
    },
    {
      "u": 0.9198,
      "v": 0.53129,
      "height_m": 12.29,
      "radius_m": 3.64
    },
    {
      "u": 0.95757,
      "v": 0.53646,
      "height_m": 8.4,
      "radius_m": 3.06
    },
    {
      "u": 0.98488,
      "v": 0.53326,
      "height_m": 9.3,
      "radius_m": 2.94
    },
    {
      "u": 0.07449,
      "v": 0.54754,
      "height_m": 8.59,
      "radius_m": 2.45
    },
    {
      "u": 0.40452,
      "v": 0.55007,
      "height_m": 11.98,
      "radius_m": 3.75
    },
    {
      "u": 0.46933,
      "v": 0.55003,
      "height_m": 10.8,
      "radius_m": 3.22
    },
    {
      "u": 0.62634,
      "v": 0.54925,
      "height_m": 10.47,
      "radius_m": 3.52
    },
    {
      "u": 0.64266,
      "v": 0.54951,
      "height_m": 6.93,
      "radius_m": 2.54
    },
    {
      "u": 0.70328,
      "v": 0.5465,
      "height_m": 10.14,
      "radius_m": 3.32
    },
    {
      "u": 0.74026,
      "v": 0.551,
      "height_m": 10.66,
      "radius_m": 3.63
    },
    {
      "u": 0.76368,
      "v": 0.54384,
      "height_m": 11.55,
      "radius_m": 3.65
    },
    {
      "u": 0.78113,
      "v": 0.55142,
      "height_m": 12.59,
      "radius_m": 3.69
    },
    {
      "u": 0.81778,
      "v": 0.54526,
      "height_m": 8.64,
      "radius_m": 3.13
    },
    {
      "u": 0.87337,
      "v": 0.55101,
      "height_m": 10.81,
      "radius_m": 3.05
    },
    {
      "u": 0.95809,
      "v": 0.54655,
      "height_m": 9.83,
      "radius_m": 2.73
    },
    {
      "u": 0.03546,
      "v": 0.55954,
      "height_m": 10.91,
      "radius_m": 3.02
    },
    {
      "u": 0.19449,
      "v": 0.56204,
      "height_m": 11.74,
      "radius_m": 3.41
    },
    {
      "u": 0.41799,
      "v": 0.567,
      "height_m": 11.62,
      "radius_m": 3.49
    },
    {
      "u": 0.49153,
      "v": 0.56569,
      "height_m": 8.25,
      "radius_m": 2.93
    },
    {
      "u": 0.59124,
      "v": 0.55914,
      "height_m": 10.68,
      "radius_m": 3.89
    },
    {
      "u": 0.61757,
      "v": 0.56601,
      "height_m": 11.17,
      "radius_m": 3.66
    },
    {
      "u": 0.87424,
      "v": 0.56536,
      "height_m": 8.9,
      "radius_m": 2.67
    },
    {
      "u": 0.93813,
      "v": 0.56379,
      "height_m": 8.09,
      "radius_m": 2.93
    },
    {
      "u": 0.21636,
      "v": 0.57394,
      "height_m": 12.0,
      "radius_m": 3.84
    },
    {
      "u": 0.36143,
      "v": 0.57791,
      "height_m": 11.22,
      "radius_m": 3.61
    },
    {
      "u": 0.52942,
      "v": 0.57869,
      "height_m": 11.8,
      "radius_m": 3.91
    },
    {
      "u": 0.60543,
      "v": 0.57495,
      "height_m": 13.06,
      "radius_m": 3.83
    },
    {
      "u": 0.73098,
      "v": 0.57736,
      "height_m": 11.89,
      "radius_m": 3.61
    },
    {
      "u": 0.80447,
      "v": 0.57557,
      "height_m": 9.8,
      "radius_m": 2.95
    },
    {
      "u": 0.88465,
      "v": 0.57841,
      "height_m": 10.69,
      "radius_m": 3.7
    },
    {
      "u": 0.95068,
      "v": 0.58032,
      "height_m": 9.29,
      "radius_m": 2.52
    },
    {
      "u": 0.19754,
      "v": 0.59181,
      "height_m": 8.62,
      "radius_m": 2.61
    },
    {
      "u": 0.27023,
      "v": 0.58559,
      "height_m": 13.26,
      "radius_m": 3.99
    },
    {
      "u": 0.28536,
      "v": 0.59252,
      "height_m": 12.74,
      "radius_m": 4.0
    },
    {
      "u": 0.29567,
      "v": 0.5924,
      "height_m": 12.57,
      "radius_m": 3.99
    },
    {
      "u": 0.54706,
      "v": 0.59501,
      "height_m": 13.42,
      "radius_m": 3.96
    },
    {
      "u": 0.6245,
      "v": 0.592,
      "height_m": 9.36,
      "radius_m": 3.19
    },
    {
      "u": 0.78023,
      "v": 0.59079,
      "height_m": 10.5,
      "radius_m": 3.53
    },
    {
      "u": 0.7922,
      "v": 0.58808,
      "height_m": 9.08,
      "radius_m": 3.33
    },
    {
      "u": 0.94783,
      "v": 0.58909,
      "height_m": 9.97,
      "radius_m": 3.52
    },
    {
      "u": 0.97141,
      "v": 0.59322,
      "height_m": 11.25,
      "radius_m": 4.0
    },
    {
      "u": 0.09215,
      "v": 0.60561,
      "height_m": 13.03,
      "radius_m": 3.96
    },
    {
      "u": 0.2646,
      "v": 0.60728,
      "height_m": 12.42,
      "radius_m": 3.99
    },
    {
      "u": 0.61413,
      "v": 0.60598,
      "height_m": 10.53,
      "radius_m": 3.51
    },
    {
      "u": 0.66927,
      "v": 0.6048,
      "height_m": 12.84,
      "radius_m": 3.84
    },
    {
      "u": 0.69252,
      "v": 0.60896,
      "height_m": 8.37,
      "radius_m": 2.75
    },
    {
      "u": 0.74108,
      "v": 0.60745,
      "height_m": 12.01,
      "radius_m": 3.64
    },
    {
      "u": 0.87338,
      "v": 0.60063,
      "height_m": 9.36,
      "radius_m": 2.57
    },
    {
      "u": 0.90412,
      "v": 0.60678,
      "height_m": 9.34,
      "radius_m": 3.27
    },
    {
      "u": 0.91829,
      "v": 0.60663,
      "height_m": 10.13,
      "radius_m": 3.62
    },
    {
      "u": 0.30807,
      "v": 0.62276,
      "height_m": 11.71,
      "radius_m": 4.0
    },
    {
      "u": 0.51614,
      "v": 0.61532,
      "height_m": 8.75,
      "radius_m": 2.97
    },
    {
      "u": 0.56974,
      "v": 0.61718,
      "height_m": 11.69,
      "radius_m": 3.67
    },
    {
      "u": 0.63817,
      "v": 0.61828,
      "height_m": 12.79,
      "radius_m": 3.8
    },
    {
      "u": 0.77092,
      "v": 0.61927,
      "height_m": 10.04,
      "radius_m": 3.59
    },
    {
      "u": 0.80231,
      "v": 0.6175,
      "height_m": 9.82,
      "radius_m": 3.16
    },
    {
      "u": 0.88161,
      "v": 0.61696,
      "height_m": 8.25,
      "radius_m": 2.56
    },
    {
      "u": 0.98472,
      "v": 0.62129,
      "height_m": 9.29,
      "radius_m": 3.41
    },
    {
      "u": 0.9981,
      "v": 0.62216,
      "height_m": 10.57,
      "radius_m": 3.37
    },
    {
      "u": 0.08356,
      "v": 0.62749,
      "height_m": 11.75,
      "radius_m": 3.88
    },
    {
      "u": 0.09586,
      "v": 0.63536,
      "height_m": 10.22,
      "radius_m": 3.55
    },
    {
      "u": 0.52886,
      "v": 0.63375,
      "height_m": 11.49,
      "radius_m": 3.26
    },
    {
      "u": 0.53995,
      "v": 0.63216,
      "height_m": 10.92,
      "radius_m": 3.63
    },
    {
      "u": 0.56862,
      "v": 0.63562,
      "height_m": 11.03,
      "radius_m": 3.72
    },
    {
      "u": 0.60898,
      "v": 0.63368,
      "height_m": 9.72,
      "radius_m": 3.5
    },
    {
      "u": 0.64824,
      "v": 0.63408,
      "height_m": 12.0,
      "radius_m": 3.41
    },
    {
      "u": 0.65772,
      "v": 0.63403,
      "height_m": 10.44,
      "radius_m": 3.73
    },
    {
      "u": 0.67439,
      "v": 0.63541,
      "height_m": 10.67,
      "radius_m": 3.76
    },
    {
      "u": 0.73042,
      "v": 0.62717,
      "height_m": 10.62,
      "radius_m": 3.1
    },
    {
      "u": 0.78554,
      "v": 0.63187,
      "height_m": 10.09,
      "radius_m": 2.81
    },
    {
      "u": 0.95823,
      "v": 0.63192,
      "height_m": 9.43,
      "radius_m": 3.32
    },
    {
      "u": 0.98501,
      "v": 0.63249,
      "height_m": 11.99,
      "radius_m": 3.67
    },
    {
      "u": 0.55365,
      "v": 0.64474,
      "height_m": 11.21,
      "radius_m": 3.83
    },
    {
      "u": 0.65367,
      "v": 0.64942,
      "height_m": 11.49,
      "radius_m": 3.38
    },
    {
      "u": 0.68484,
      "v": 0.64684,
      "height_m": 10.0,
      "radius_m": 2.71
    },
    {
      "u": 0.77334,
      "v": 0.64618,
      "height_m": 9.11,
      "radius_m": 3.14
    },
    {
      "u": 0.83994,
      "v": 0.64462,
      "height_m": 7.91,
      "radius_m": 2.75
    },
    {
      "u": 0.84688,
      "v": 0.64129,
      "height_m": 9.03,
      "radius_m": 3.17
    },
    {
      "u": 0.92786,
      "v": 0.65006,
      "height_m": 12.93,
      "radius_m": 3.67
    },
    {
      "u": 0.98118,
      "v": 0.64407,
      "height_m": 10.88,
      "radius_m": 3.6
    },
    {
      "u": 0.11768,
      "v": 0.65858,
      "height_m": 7.06,
      "radius_m": 2.5
    },
    {
      "u": 0.27559,
      "v": 0.65676,
      "height_m": 13.8,
      "radius_m": 3.99
    },
    {
      "u": 0.38378,
      "v": 0.6567,
      "height_m": 12.21,
      "radius_m": 3.94
    },
    {
      "u": 0.59452,
      "v": 0.6551,
      "height_m": 8.53,
      "radius_m": 2.63
    },
    {
      "u": 0.62691,
      "v": 0.65813,
      "height_m": 10.76,
      "radius_m": 3.39
    },
    {
      "u": 0.64258,
      "v": 0.662,
      "height_m": 10.17,
      "radius_m": 3.07
    },
    {
      "u": 0.87337,
      "v": 0.65574,
      "height_m": 12.29,
      "radius_m": 3.89
    },
    {
      "u": 0.08395,
      "v": 0.67828,
      "height_m": 12.45,
      "radius_m": 3.5
    },
    {
      "u": 0.09616,
      "v": 0.67169,
      "height_m": 10.84,
      "radius_m": 3.48
    },
    {
      "u": 0.20777,
      "v": 0.67806,
      "height_m": 12.39,
      "radius_m": 3.9
    },
    {
      "u": 0.26494,
      "v": 0.66979,
      "height_m": 11.92,
      "radius_m": 3.96
    },
    {
      "u": 0.40926,
      "v": 0.67113,
      "height_m": 7.74,
      "radius_m": 2.7
    },
    {
      "u": 0.66168,
      "v": 0.67226,
      "height_m": 9.62,
      "radius_m": 3.38
    },
    {
      "u": 0.76873,
      "v": 0.67827,
      "height_m": 11.62,
      "radius_m": 3.25
    },
    {
      "u": 0.79293,
      "v": 0.67462,
      "height_m": 10.59,
      "radius_m": 3.2
    },
    {
      "u": 0.80277,
      "v": 0.67628,
      "height_m": 10.09,
      "radius_m": 3.41
    },
    {
      "u": 0.87084,
      "v": 0.67734,
      "height_m": 13.32,
      "radius_m": 4.0
    },
    {
      "u": 0.88101,
      "v": 0.67084,
      "height_m": 10.32,
      "radius_m": 3.77
    },
    {
      "u": 0.98408,
      "v": 0.6698,
      "height_m": 13.23,
      "radius_m": 3.95
    },
    {
      "u": 0.20823,
      "v": 0.6873,
      "height_m": 12.61,
      "radius_m": 3.98
    },
    {
      "u": 0.23538,
      "v": 0.68857,
      "height_m": 11.55,
      "radius_m": 4.0
    },
    {
      "u": 0.40416,
      "v": 0.68565,
      "height_m": 12.08,
      "radius_m": 3.69
    },
    {
      "u": 0.57252,
      "v": 0.68823,
      "height_m": 11.67,
      "radius_m": 3.74
    },
    {
      "u": 0.62727,
      "v": 0.69152,
      "height_m": 9.89,
      "radius_m": 3.47
    },
    {
      "u": 0.7254,
      "v": 0.6922,
      "height_m": 11.4,
      "radius_m": 3.58
    },
    {
      "u": 0.75373,
      "v": 0.68911,
      "height_m": 9.98,
      "radius_m": 3.3
    },
    {
      "u": 0.76344,
      "v": 0.69036,
      "height_m": 11.62,
      "radius_m": 3.52
    },
    {
      "u": 0.79369,
      "v": 0.68533,
      "height_m": 12.21,
      "radius_m": 3.48
    },
    {
      "u": 0.86318,
      "v": 0.68972,
      "height_m": 9.86,
      "radius_m": 3.51
    },
    {
      "u": 0.97996,
      "v": 0.68624,
      "height_m": 9.1,
      "radius_m": 2.63
    },
    {
      "u": 0.24899,
      "v": 0.69888,
      "height_m": 13.33,
      "radius_m": 3.98
    },
    {
      "u": 0.26439,
      "v": 0.70362,
      "height_m": 11.05,
      "radius_m": 3.8
    },
    {
      "u": 0.27382,
      "v": 0.70144,
      "height_m": 13.76,
      "radius_m": 3.99
    },
    {
      "u": 0.31943,
      "v": 0.70242,
      "height_m": 11.02,
      "radius_m": 4.0
    },
    {
      "u": 0.37156,
      "v": 0.69903,
      "height_m": 13.28,
      "radius_m": 3.96
    },
    {
      "u": 0.41389,
      "v": 0.69925,
      "height_m": 7.89,
      "radius_m": 2.59
    },
    {
      "u": 0.57084,
      "v": 0.69917,
      "height_m": 11.74,
      "radius_m": 3.71
    },
    {
      "u": 0.60629,
      "v": 0.70232,
      "height_m": 11.71,
      "radius_m": 3.94
    },
    {
      "u": 0.62514,
      "v": 0.69932,
      "height_m": 11.5,
      "radius_m": 3.66
    },
    {
      "u": 0.6798,
      "v": 0.70625,
      "height_m": 11.02,
      "radius_m": 3.43
    },
    {
      "u": 0.77378,
      "v": 0.69926,
      "height_m": 9.94,
      "radius_m": 3.13
    },
    {
      "u": 0.85807,
      "v": 0.70407,
      "height_m": 10.29,
      "radius_m": 3.25
    },
    {
      "u": 0.91499,
      "v": 0.70597,
      "height_m": 13.25,
      "radius_m": 3.93
    },
    {
      "u": 0.96391,
      "v": 0.70411,
      "height_m": 10.79,
      "radius_m": 3.89
    },
    {
      "u": 0.22413,
      "v": 0.71454,
      "height_m": 11.68,
      "radius_m": 3.95
    },
    {
      "u": 0.5463,
      "v": 0.71216,
      "height_m": 13.4,
      "radius_m": 3.87
    },
    {
      "u": 0.60924,
      "v": 0.7125,
      "height_m": 11.11,
      "radius_m": 3.85
    },
    {
      "u": 0.68532,
      "v": 0.71559,
      "height_m": 9.56,
      "radius_m": 3.02
    },
    {
      "u": 0.75186,
      "v": 0.71857,
      "height_m": 12.78,
      "radius_m": 3.72
    },
    {
      "u": 0.7633,
      "v": 0.71117,
      "height_m": 10.74,
      "radius_m": 3.71
    },
    {
      "u": 0.10306,
      "v": 0.7323,
      "height_m": 9.04,
      "radius_m": 2.57
    },
    {
      "u": 0.1523,
      "v": 0.72739,
      "height_m": 9.93,
      "radius_m": 3.39
    },
    {
      "u": 0.21776,
      "v": 0.7261,
      "height_m": 13.71,
      "radius_m": 3.99
    },
    {
      "u": 0.53717,
      "v": 0.72758,
      "height_m": 11.64,
      "radius_m": 3.76
    },
    {
      "u": 0.58494,
      "v": 0.72703,
      "height_m": 10.5,
      "radius_m": 3.74
    },
    {
      "u": 0.59694,
      "v": 0.72856,
      "height_m": 12.84,
      "radius_m": 3.81
    },
    {
      "u": 0.63099,
      "v": 0.73072,
      "height_m": 11.86,
      "radius_m": 3.53
    },
    {
      "u": 0.63663,
      "v": 0.73298,
      "height_m": 11.91,
      "radius_m": 3.77
    },
    {
      "u": 0.73148,
      "v": 0.72466,
      "height_m": 10.76,
      "radius_m": 3.66
    },
    {
      "u": 0.73763,
      "v": 0.73055,
      "height_m": 11.83,
      "radius_m": 3.69
    },
    {
      "u": 0.77243,
      "v": 0.72769,
      "height_m": 9.81,
      "radius_m": 3.61
    },
    {
      "u": 0.85277,
      "v": 0.73046,
      "height_m": 11.23,
      "radius_m": 3.41
    },
    {
      "u": 0.07004,
      "v": 0.74764,
      "height_m": 7.99,
      "radius_m": 2.61
    },
    {
      "u": 0.26461,
      "v": 0.74528,
      "height_m": 11.21,
      "radius_m": 3.53
    },
    {
      "u": 0.32013,
      "v": 0.74335,
      "height_m": 11.52,
      "radius_m": 4.0
    },
    {
      "u": 0.69563,
      "v": 0.74226,
      "height_m": 11.96,
      "radius_m": 3.45
    },
    {
      "u": 0.70648,
      "v": 0.74608,
      "height_m": 11.36,
      "radius_m": 3.33
    },
    {
      "u": 0.73829,
      "v": 0.74471,
      "height_m": 10.88,
      "radius_m": 3.83
    },
    {
      "u": 0.80417,
      "v": 0.74284,
      "height_m": 9.57,
      "radius_m": 3.46
    },
    {
      "u": 0.82501,
      "v": 0.74312,
      "height_m": 12.04,
      "radius_m": 3.38
    },
    {
      "u": 0.83556,
      "v": 0.74505,
      "height_m": 10.22,
      "radius_m": 3.47
    },
    {
      "u": 0.04219,
      "v": 0.76167,
      "height_m": 10.84,
      "radius_m": 3.1
    },
    {
      "u": 0.19299,
      "v": 0.75924,
      "height_m": 12.13,
      "radius_m": 4.0
    },
    {
      "u": 0.21821,
      "v": 0.75351,
      "height_m": 11.75,
      "radius_m": 4.0
    },
    {
      "u": 0.42932,
      "v": 0.75299,
      "height_m": 12.57,
      "radius_m": 3.69
    },
    {
      "u": 0.62613,
      "v": 0.75343,
      "height_m": 11.79,
      "radius_m": 3.94
    },
    {
      "u": 0.68337,
      "v": 0.75336,
      "height_m": 10.52,
      "radius_m": 3.25
    },
    {
      "u": 0.74155,
      "v": 0.75542,
      "height_m": 10.26,
      "radius_m": 3.65
    },
    {
      "u": 0.76105,
      "v": 0.75247,
      "height_m": 11.08,
      "radius_m": 3.72
    },
    {
      "u": 0.84138,
      "v": 0.75882,
      "height_m": 10.45,
      "radius_m": 3.57
    },
    {
      "u": 0.86262,
      "v": 0.75494,
      "height_m": 12.79,
      "radius_m": 3.65
    },
    {
      "u": 0.88721,
      "v": 0.75304,
      "height_m": 13.14,
      "radius_m": 3.8
    },
    {
      "u": 0.89368,
      "v": 0.75487,
      "height_m": 10.81,
      "radius_m": 3.9
    },
    {
      "u": 0.9203,
      "v": 0.75286,
      "height_m": 12.67,
      "radius_m": 4.0
    },
    {
      "u": 0.07527,
      "v": 0.76936,
      "height_m": 7.85,
      "radius_m": 2.55
    },
    {
      "u": 0.24198,
      "v": 0.76754,
      "height_m": 11.79,
      "radius_m": 3.99
    },
    {
      "u": 0.27553,
      "v": 0.77123,
      "height_m": 12.61,
      "radius_m": 4.0
    },
    {
      "u": 0.31734,
      "v": 0.77135,
      "height_m": 12.71,
      "radius_m": 3.99
    },
    {
      "u": 0.45867,
      "v": 0.76846,
      "height_m": 11.39,
      "radius_m": 3.89
    },
    {
      "u": 0.47239,
      "v": 0.76959,
      "height_m": 13.09,
      "radius_m": 3.73
    },
    {
      "u": 0.52472,
      "v": 0.77517,
      "height_m": 12.4,
      "radius_m": 3.75
    },
    {
      "u": 0.5751,
      "v": 0.76789,
      "height_m": 12.31,
      "radius_m": 3.89
    },
    {
      "u": 0.6294,
      "v": 0.76915,
      "height_m": 13.63,
      "radius_m": 3.95
    },
    {
      "u": 0.68048,
      "v": 0.77567,
      "height_m": 13.05,
      "radius_m": 3.89
    },
    {
      "u": 0.77598,
      "v": 0.76616,
      "height_m": 11.0,
      "radius_m": 3.81
    },
    {
      "u": 0.78443,
      "v": 0.76727,
      "height_m": 10.36,
      "radius_m": 3.54
    },
    {
      "u": 0.8197,
      "v": 0.7725,
      "height_m": 11.25,
      "radius_m": 3.2
    },
    {
      "u": 0.08172,
      "v": 0.77988,
      "height_m": 8.48,
      "radius_m": 2.47
    },
    {
      "u": 0.12454,
      "v": 0.78314,
      "height_m": 12.72,
      "radius_m": 4.0
    },
    {
      "u": 0.15787,
      "v": 0.78365,
      "height_m": 12.11,
      "radius_m": 4.0
    },
    {
      "u": 0.24213,
      "v": 0.78816,
      "height_m": 12.23,
      "radius_m": 4.0
    },
    {
      "u": 0.26001,
      "v": 0.78828,
      "height_m": 11.09,
      "radius_m": 4.0
    },
    {
      "u": 0.4364,
      "v": 0.78434,
      "height_m": 11.47,
      "radius_m": 3.82
    },
    {
      "u": 0.48598,
      "v": 0.78049,
      "height_m": 11.12,
      "radius_m": 3.87
    },
    {
      "u": 0.59618,
      "v": 0.78767,
      "height_m": 10.81,
      "radius_m": 3.84
    },
    {
      "u": 0.74638,
      "v": 0.78512,
      "height_m": 11.01,
      "radius_m": 3.75
    },
    {
      "u": 0.81964,
      "v": 0.7804,
      "height_m": 12.18,
      "radius_m": 3.71
    },
    {
      "u": 0.87205,
      "v": 0.78238,
      "height_m": 10.61,
      "radius_m": 3.7
    },
    {
      "u": 0.93013,
      "v": 0.78055,
      "height_m": 11.32,
      "radius_m": 3.86
    },
    {
      "u": 0.08018,
      "v": 0.80215,
      "height_m": 11.33,
      "radius_m": 3.99
    },
    {
      "u": 0.09183,
      "v": 0.80126,
      "height_m": 10.61,
      "radius_m": 3.25
    },
    {
      "u": 0.17308,
      "v": 0.80186,
      "height_m": 11.24,
      "radius_m": 3.73
    },
    {
      "u": 0.30584,
      "v": 0.79823,
      "height_m": 12.46,
      "radius_m": 3.96
    },
    {
      "u": 0.32694,
      "v": 0.80007,
      "height_m": 13.42,
      "radius_m": 3.98
    },
    {
      "u": 0.46478,
      "v": 0.79935,
      "height_m": 11.58,
      "radius_m": 3.66
    },
    {
      "u": 0.48039,
      "v": 0.80268,
      "height_m": 10.52,
      "radius_m": 3.36
    },
    {
      "u": 0.55303,
      "v": 0.80254,
      "height_m": 12.68,
      "radius_m": 3.75
    },
    {
      "u": 0.5977,
      "v": 0.7968,
      "height_m": 11.64,
      "radius_m": 3.88
    },
    {
      "u": 0.60609,
      "v": 0.79513,
      "height_m": 11.32,
      "radius_m": 3.66
    },
    {
      "u": 0.63105,
      "v": 0.80307,
      "height_m": 13.13,
      "radius_m": 3.99
    },
    {
      "u": 0.68482,
      "v": 0.80058,
      "height_m": 13.14,
      "radius_m": 3.93
    },
    {
      "u": 0.69428,
      "v": 0.7993,
      "height_m": 11.68,
      "radius_m": 3.98
    },
    {
      "u": 0.70556,
      "v": 0.79462,
      "height_m": 12.74,
      "radius_m": 3.63
    },
    {
      "u": 0.72,
      "v": 0.79447,
      "height_m": 8.91,
      "radius_m": 3.31
    },
    {
      "u": 0.80801,
      "v": 0.79457,
      "height_m": 11.18,
      "radius_m": 3.94
    },
    {
      "u": 0.85292,
      "v": 0.80062,
      "height_m": 13.29,
      "radius_m": 3.92
    },
    {
      "u": 0.86218,
      "v": 0.79478,
      "height_m": 10.72,
      "radius_m": 3.21
    },
    {
      "u": 0.87219,
      "v": 0.79554,
      "height_m": 10.5,
      "radius_m": 3.74
    },
    {
      "u": 0.09454,
      "v": 0.81312,
      "height_m": 13.68,
      "radius_m": 3.98
    },
    {
      "u": 0.12991,
      "v": 0.8134,
      "height_m": 13.39,
      "radius_m": 3.92
    },
    {
      "u": 0.22486,
      "v": 0.81289,
      "height_m": 12.31,
      "radius_m": 4.0
    },
    {
      "u": 0.24896,
      "v": 0.81063,
      "height_m": 13.48,
      "radius_m": 3.96
    },
    {
      "u": 0.33513,
      "v": 0.81299,
      "height_m": 12.77,
      "radius_m": 3.95
    },
    {
      "u": 0.44853,
      "v": 0.81191,
      "height_m": 13.59,
      "radius_m": 3.99
    },
    {
      "u": 0.50943,
      "v": 0.81406,
      "height_m": 9.54,
      "radius_m": 3.46
    },
    {
      "u": 0.56106,
      "v": 0.81651,
      "height_m": 7.1,
      "radius_m": 2.62
    },
    {
      "u": 0.58106,
      "v": 0.81552,
      "height_m": 11.45,
      "radius_m": 3.75
    },
    {
      "u": 0.65822,
      "v": 0.8111,
      "height_m": 11.3,
      "radius_m": 3.96
    },
    {
      "u": 0.69234,
      "v": 0.81367,
      "height_m": 12.14,
      "radius_m": 3.96
    },
    {
      "u": 0.71875,
      "v": 0.81552,
      "height_m": 12.85,
      "radius_m": 3.9
    },
    {
      "u": 0.74802,
      "v": 0.81063,
      "height_m": 10.88,
      "radius_m": 3.46
    },
    {
      "u": 0.78295,
      "v": 0.80886,
      "height_m": 10.44,
      "radius_m": 3.06
    },
    {
      "u": 0.89631,
      "v": 0.80789,
      "height_m": 11.72,
      "radius_m": 3.94
    },
    {
      "u": 0.12775,
      "v": 0.82228,
      "height_m": 12.59,
      "radius_m": 3.93
    },
    {
      "u": 0.16187,
      "v": 0.82416,
      "height_m": 11.9,
      "radius_m": 3.95
    },
    {
      "u": 0.19597,
      "v": 0.82512,
      "height_m": 11.17,
      "radius_m": 3.99
    },
    {
      "u": 0.2799,
      "v": 0.82568,
      "height_m": 10.92,
      "radius_m": 3.79
    },
    {
      "u": 0.31319,
      "v": 0.82849,
      "height_m": 10.62,
      "radius_m": 3.78
    },
    {
      "u": 0.60377,
      "v": 0.82715,
      "height_m": 13.0,
      "radius_m": 3.94
    },
    {
      "u": 0.62456,
      "v": 0.82963,
      "height_m": 11.69,
      "radius_m": 3.74
    },
    {
      "u": 0.67021,
      "v": 0.82575,
      "height_m": 12.66,
      "radius_m": 4.0
    },
    {
      "u": 0.69813,
      "v": 0.82554,
      "height_m": 12.63,
      "radius_m": 3.77
    },
    {
      "u": 0.71293,
      "v": 0.83,
      "height_m": 10.82,
      "radius_m": 3.9
    },
    {
      "u": 0.75073,
      "v": 0.82967,
      "height_m": 11.63,
      "radius_m": 3.83
    },
    {
      "u": 0.85209,
      "v": 0.82763,
      "height_m": 11.99,
      "radius_m": 3.95
    },
    {
      "u": 0.89252,
      "v": 0.82293,
      "height_m": 13.41,
      "radius_m": 3.94
    },
    {
      "u": 0.19475,
      "v": 0.84327,
      "height_m": 12.78,
      "radius_m": 3.99
    },
    {
      "u": 0.28503,
      "v": 0.84257,
      "height_m": 11.91,
      "radius_m": 4.0
    },
    {
      "u": 0.29229,
      "v": 0.84141,
      "height_m": 13.89,
      "radius_m": 3.97
    },
    {
      "u": 0.47135,
      "v": 0.84438,
      "height_m": 12.87,
      "radius_m": 3.99
    },
    {
      "u": 0.62008,
      "v": 0.84386,
      "height_m": 10.53,
      "radius_m": 3.67
    },
    {
      "u": 0.67352,
      "v": 0.83575,
      "height_m": 11.07,
      "radius_m": 3.92
    },
    {
      "u": 0.71576,
      "v": 0.83991,
      "height_m": 12.37,
      "radius_m": 3.88
    },
    {
      "u": 0.89198,
      "v": 0.84409,
      "height_m": 12.5,
      "radius_m": 3.99
    },
    {
      "u": 0.19776,
      "v": 0.85359,
      "height_m": 13.83,
      "radius_m": 4.0
    },
    {
      "u": 0.2479,
      "v": 0.85378,
      "height_m": 10.96,
      "radius_m": 3.97
    },
    {
      "u": 0.37471,
      "v": 0.85849,
      "height_m": 11.1,
      "radius_m": 3.82
    },
    {
      "u": 0.40835,
      "v": 0.85558,
      "height_m": 11.7,
      "radius_m": 3.84
    },
    {
      "u": 0.43579,
      "v": 0.84977,
      "height_m": 11.34,
      "radius_m": 3.99
    },
    {
      "u": 0.46015,
      "v": 0.85569,
      "height_m": 11.77,
      "radius_m": 4.0
    },
    {
      "u": 0.54054,
      "v": 0.85238,
      "height_m": 13.23,
      "radius_m": 3.89
    },
    {
      "u": 0.65181,
      "v": 0.85693,
      "height_m": 13.4,
      "radius_m": 3.9
    },
    {
      "u": 0.70577,
      "v": 0.85533,
      "height_m": 11.59,
      "radius_m": 3.73
    },
    {
      "u": 0.75333,
      "v": 0.85805,
      "height_m": 9.77,
      "radius_m": 3.49
    },
    {
      "u": 0.81707,
      "v": 0.85831,
      "height_m": 12.31,
      "radius_m": 3.6
    },
    {
      "u": 0.82927,
      "v": 0.84944,
      "height_m": 13.91,
      "radius_m": 3.99
    },
    {
      "u": 0.8859,
      "v": 0.8562,
      "height_m": 12.0,
      "radius_m": 3.81
    },
    {
      "u": 0.89179,
      "v": 0.85315,
      "height_m": 10.73,
      "radius_m": 3.2
    },
    {
      "u": 0.13859,
      "v": 0.86415,
      "height_m": 11.77,
      "radius_m": 3.81
    },
    {
      "u": 0.16195,
      "v": 0.86848,
      "height_m": 13.19,
      "radius_m": 3.97
    },
    {
      "u": 0.17099,
      "v": 0.86439,
      "height_m": 11.76,
      "radius_m": 3.89
    },
    {
      "u": 0.1859,
      "v": 0.86743,
      "height_m": 11.72,
      "radius_m": 3.85
    },
    {
      "u": 0.37415,
      "v": 0.86803,
      "height_m": 11.78,
      "radius_m": 3.87
    },
    {
      "u": 0.39267,
      "v": 0.87143,
      "height_m": 13.32,
      "radius_m": 3.94
    },
    {
      "u": 0.41315,
      "v": 0.86735,
      "height_m": 12.53,
      "radius_m": 3.89
    },
    {
      "u": 0.42601,
      "v": 0.86982,
      "height_m": 12.51,
      "radius_m": 3.95
    },
    {
      "u": 0.51621,
      "v": 0.87023,
      "height_m": 11.23,
      "radius_m": 3.99
    },
    {
      "u": 0.52668,
      "v": 0.86424,
      "height_m": 13.17,
      "radius_m": 3.99
    },
    {
      "u": 0.57178,
      "v": 0.87049,
      "height_m": 9.09,
      "radius_m": 3.27
    },
    {
      "u": 0.5872,
      "v": 0.87012,
      "height_m": 10.74,
      "radius_m": 3.9
    },
    {
      "u": 0.66854,
      "v": 0.86707,
      "height_m": 12.75,
      "radius_m": 3.6
    },
    {
      "u": 0.69227,
      "v": 0.86949,
      "height_m": 12.02,
      "radius_m": 3.92
    },
    {
      "u": 0.71762,
      "v": 0.86582,
      "height_m": 13.48,
      "radius_m": 3.89
    },
    {
      "u": 0.74211,
      "v": 0.8649,
      "height_m": 11.23,
      "radius_m": 3.82
    },
    {
      "u": 0.77459,
      "v": 0.87205,
      "height_m": 12.46,
      "radius_m": 3.97
    },
    {
      "u": 0.80232,
      "v": 0.86893,
      "height_m": 8.79,
      "radius_m": 3.04
    },
    {
      "u": 0.85989,
      "v": 0.86597,
      "height_m": 13.06,
      "radius_m": 3.98
    },
    {
      "u": 0.87434,
      "v": 0.87035,
      "height_m": 12.19,
      "radius_m": 3.74
    },
    {
      "u": 0.22025,
      "v": 0.88173,
      "height_m": 11.33,
      "radius_m": 3.44
    },
    {
      "u": 0.31405,
      "v": 0.88092,
      "height_m": 11.38,
      "radius_m": 3.69
    },
    {
      "u": 0.49519,
      "v": 0.88064,
      "height_m": 12.51,
      "radius_m": 3.97
    },
    {
      "u": 0.60247,
      "v": 0.88547,
      "height_m": 11.12,
      "radius_m": 3.84
    },
    {
      "u": 0.64694,
      "v": 0.87838,
      "height_m": 9.48,
      "radius_m": 3.39
    },
    {
      "u": 0.78066,
      "v": 0.88094,
      "height_m": 12.62,
      "radius_m": 3.88
    },
    {
      "u": 0.1836,
      "v": 0.89101,
      "height_m": 9.81,
      "radius_m": 3.5
    },
    {
      "u": 0.25238,
      "v": 0.89499,
      "height_m": 11.71,
      "radius_m": 3.34
    },
    {
      "u": 0.29739,
      "v": 0.89162,
      "height_m": 9.47,
      "radius_m": 2.54
    },
    {
      "u": 0.56124,
      "v": 0.89631,
      "height_m": 12.08,
      "radius_m": 3.76
    },
    {
      "u": 0.62514,
      "v": 0.89536,
      "height_m": 11.16,
      "radius_m": 3.61
    },
    {
      "u": 0.75326,
      "v": 0.89413,
      "height_m": 11.16,
      "radius_m": 3.96
    },
    {
      "u": 0.77215,
      "v": 0.89358,
      "height_m": 13.05,
      "radius_m": 3.96
    },
    {
      "u": 0.82637,
      "v": 0.89871,
      "height_m": 12.02,
      "radius_m": 3.98
    },
    {
      "u": 0.84088,
      "v": 0.89523,
      "height_m": 11.39,
      "radius_m": 3.92
    },
    {
      "u": 0.84771,
      "v": 0.89376,
      "height_m": 11.27,
      "radius_m": 3.97
    },
    {
      "u": 0.86837,
      "v": 0.89955,
      "height_m": 13.27,
      "radius_m": 3.96
    },
    {
      "u": 0.37443,
      "v": 0.91103,
      "height_m": 9.71,
      "radius_m": 3.52
    },
    {
      "u": 0.63051,
      "v": 0.90869,
      "height_m": 10.85,
      "radius_m": 3.31
    },
    {
      "u": 0.63776,
      "v": 0.91273,
      "height_m": 9.59,
      "radius_m": 3.32
    },
    {
      "u": 0.85238,
      "v": 0.90808,
      "height_m": 10.85,
      "radius_m": 3.81
    },
    {
      "u": 0.86414,
      "v": 0.90821,
      "height_m": 13.3,
      "radius_m": 3.82
    },
    {
      "u": 0.45857,
      "v": 0.92017,
      "height_m": 10.1,
      "radius_m": 3.19
    },
    {
      "u": 0.61339,
      "v": 0.92222,
      "height_m": 12.27,
      "radius_m": 3.87
    },
    {
      "u": 0.83661,
      "v": 0.92075,
      "height_m": 12.28,
      "radius_m": 3.76
    },
    {
      "u": 0.63737,
      "v": 0.93775,
      "height_m": 9.49,
      "radius_m": 2.92
    },
    {
      "u": 0.66886,
      "v": 0.93339,
      "height_m": 10.7,
      "radius_m": 2.96
    },
    {
      "u": 0.83825,
      "v": 0.94021,
      "height_m": 9.5,
      "radius_m": 3.45
    },
    {
      "u": 0.20235,
      "v": 0.95118,
      "height_m": 12.93,
      "radius_m": 4.0
    },
    {
      "u": 0.2816,
      "v": 0.95586,
      "height_m": 11.56,
      "radius_m": 3.43
    },
    {
      "u": 0.24893,
      "v": 0.96859,
      "height_m": 11.01,
      "radius_m": 3.96
    },
    {
      "u": 0.26389,
      "v": 0.96677,
      "height_m": 12.14,
      "radius_m": 3.99
    },
    {
      "u": 0.36466,
      "v": 0.96045,
      "height_m": 11.49,
      "radius_m": 3.98
    },
    {
      "u": 0.38678,
      "v": 0.96146,
      "height_m": 11.05,
      "radius_m": 4.0
    },
    {
      "u": 0.25826,
      "v": 0.97805,
      "height_m": 11.15,
      "radius_m": 3.86
    },
    {
      "u": 0.29233,
      "v": 0.98195,
      "height_m": 11.14,
      "radius_m": 3.96
    },
    {
      "u": 0.53161,
      "v": 0.97564,
      "height_m": 12.5,
      "radius_m": 4.0
    },
    {
      "u": 0.54892,
      "v": 0.97589,
      "height_m": 11.68,
      "radius_m": 4.0
    },
    {
      "u": 0.61993,
      "v": 0.9782,
      "height_m": 10.51,
      "radius_m": 3.63
    },
    {
      "u": 0.64754,
      "v": 0.97659,
      "height_m": 11.91,
      "radius_m": 3.54
    },
    {
      "u": 0.67165,
      "v": 0.98267,
      "height_m": 12.34,
      "radius_m": 3.62
    },
    {
      "u": 0.24851,
      "v": 0.99477,
      "height_m": 9.43,
      "radius_m": 2.81
    },
    {
      "u": 0.56168,
      "v": 0.99623,
      "height_m": 9.8,
      "radius_m": 3.56
    },
    {
      "u": 0.67442,
      "v": 0.99035,
      "height_m": 12.08,
      "radius_m": 3.81
    },
    {
      "u": 0.71845,
      "v": 0.99321,
      "height_m": 13.71,
      "radius_m": 3.91
    },
    {
      "u": 0.80477,
      "v": 0.99018,
      "height_m": 9.1,
      "radius_m": 2.56
    }
  ]
}